botrun_flow_lang/__init__.py
botrun_flow_lang/constants.py
botrun_flow_lang/main.py
botrun_flow_lang/main_fast.py
botrun_flow_lang/requirements.txt
botrun_flow_lang/api/__init__.py
botrun_flow_lang/api/auth_api.py
botrun_flow_lang/api/auth_utils.py
botrun_flow_lang/api/botrun_back_api.py
botrun_flow_lang/api/flow_api.py
botrun_flow_lang/api/hatch_api.py
botrun_flow_lang/api/langgraph_api.py
botrun_flow_lang/api/line_bot_api.py
botrun_flow_lang/api/model_api.py
botrun_flow_lang/api/rate_limit_api.py
botrun_flow_lang/api/routes.py
botrun_flow_lang/api/search_api.py
botrun_flow_lang/api/storage_api.py
botrun_flow_lang/api/subsidy_api.py
botrun_flow_lang/api/subsidy_api_system_prompt.txt
botrun_flow_lang/api/user_setting_api.py
botrun_flow_lang/api/version_api.py
botrun_flow_lang/api/youtube_api.py
botrun_flow_lang/langgraph_agents/__init__.py
botrun_flow_lang/langgraph_agents/agents/__init__.py
botrun_flow_lang/langgraph_agents/agents/agent_runner.py
botrun_flow_lang/langgraph_agents/agents/langgraph_react_agent.py
botrun_flow_lang/langgraph_agents/agents/search_agent_graph.py
botrun_flow_lang/langgraph_agents/agents/agent_tools/__init__.py
botrun_flow_lang/langgraph_agents/agents/agent_tools/step_planner.py
botrun_flow_lang/langgraph_agents/agents/checkpointer/__init__.py
botrun_flow_lang/langgraph_agents/agents/checkpointer/firestore_checkpointer.py
botrun_flow_lang/langgraph_agents/agents/gov_researcher/GOV_RESEARCHER_PRD.md
botrun_flow_lang/langgraph_agents/agents/gov_researcher/__init__.py
botrun_flow_lang/langgraph_agents/agents/gov_researcher/gemini_subsidy_graph.py
botrun_flow_lang/langgraph_agents/agents/gov_researcher/gov_researcher_2_graph.py
botrun_flow_lang/langgraph_agents/agents/gov_researcher/gov_researcher_graph.py
botrun_flow_lang/langgraph_agents/agents/tools/__init__.py
botrun_flow_lang/langgraph_agents/agents/tools/gemini_code_execution.py
botrun_flow_lang/langgraph_agents/agents/util/__init__.py
botrun_flow_lang-5.12.264.dist-info/METADATA
botrun_flow_lang-5.12.264.dist-info/WHEEL
botrun_flow_lang-5.12.264.dist-info/RECORD
