Metadata-Version: 2.4
Name: botrun-flow-lang
Version: 5.12.264
Summary: A flow language for botrun
Author-email: sebastian-hsu <sebastian.hsu@gmail.com>
License: MIT
Classifier: Development Status :: 4 - Beta
Classifier: Intended Audience :: Developers
Classifier: Programming Language :: Python :: 3
Classifier: Programming Language :: Python :: 3.11
Classifier: Programming Language :: Python :: 3.12
Requires-Python: <3.13,>=3.11
Requires-Dist: aiohttp>=3.10.8
Requires-Dist: anthropic>=0.61.0
Requires-Dist: boto3>=1.40.3
Requires-Dist: botrun-hatch>=5.12.261
Requires-Dist: botrun-log>=0.3.0
Requires-Dist: cachetools>=5.5.2
Requires-Dist: chardet>=5.2.0
Requires-Dist: deepdiff>=8.0.1
Requires-Dist: fastapi>=0.115.5
Requires-Dist: google-auth>=2.40.3
Requires-Dist: google-cloud-discoveryengine>=0.13.3
Requires-Dist: google-cloud-firestore>=2.21.0
Requires-Dist: google-cloud-logging>=3.11.4
Requires-Dist: google-cloud-storage<3,>=2.18
Requires-Dist: google-genai>=1.28.0
Requires-Dist: jinja2>=3.1.6
Requires-Dist: langchain-anthropic>=0.3.10
Requires-Dist: langchain-aws>=0.2.17
Requires-Dist: langchain-community>=0.3.27
Requires-Dist: langchain-core>=0.3.72
Requires-Dist: langchain-google-community>=2.0.3
Requires-Dist: langchain-google-genai>=2.0.9
Requires-Dist: langchain-google-vertexai<3.0.0,>=2.1.2
Requires-Dist: langchain-mcp-adapters>=0.1.7
Requires-Dist: langchain-openai>=0.3.28
Requires-Dist: langchain>=0.3.27
Requires-Dist: langgraph-cli>=0.3.6
Requires-Dist: langgraph-supervisor>=0.0.20
Requires-Dist: langgraph>=0.6.3
Requires-Dist: line-bot-sdk>=3.17.1
Requires-Dist: mcp<1.11.0,>=1.10.1
Requires-Dist: numpy<2,>=1
Requires-Dist: openai>=1.99.1
Requires-Dist: pandas>=2.2.3
Requires-Dist: pdfminer-six==20250506
Requires-Dist: plotly>=6.0.0
Requires-Dist: pydantic-settings>=2.5.2
Requires-Dist: pypdf==6.4.2
Requires-Dist: python-multipart>=0.0.20
Requires-Dist: pytz>=2024.2
Requires-Dist: pyyaml>=6.0.2
Requires-Dist: tavily-python>=0.7.10
Requires-Dist: tiktoken>=0.10.0
Requires-Dist: tomli>=2.0.1
Requires-Dist: trustcall>=0.0.37
Requires-Dist: uvicorn>=0.34.2
Requires-Dist: wikipedia>=1.4.0
Provides-Extra: dev
Requires-Dist: build>=1.2.2; extra == 'dev'
Requires-Dist: twine>=5.1.1; extra == 'dev'
